liuhuan_mathmodel_selection/__init__.py
liuhuan_mathmodel_selection-0.1.0.dist-info/WHEEL
liuhuan_mathmodel_selection-0.1.0.dist-info/entry_points.txt
liuhuan_mathmodel_selection-0.1.0.dist-info/METADATA
liuhuan_mathmodel_selection-0.1.0.dist-info/RECORD
