Metadata-Version: 2.3
Name: liuhuan-mathmodel-selection
Version: 0.1.0
Summary: Add your description here
Author: yushui2022
Author-email: yushui2022 <xiaoyushui2022@163.com>
Requires-Dist: mcp[cli]>=1.25.0
Requires-Python: >=3.11
